libname/__init__.py
libname/dash_finance.py
dash_finance-1.0.0.dist-info/METADATA
dash_finance-1.0.0.dist-info/WHEEL
dash_finance-1.0.0.dist-info/top_level.txt
dash_finance-1.0.0.dist-info/RECORD
