Metadata-Version: 2.1
Name: dash-finance
Version: 1.0.0
Summary: Lightweight finance chart plotter 
Home-page: UNKNOWN
Author: Amit Buyo
Author-email: amitbuyo2021@gmail.com
License: UNKNOWN
Keywords: python,dash,finance,plotly
Platform: UNKNOWN
Classifier: Development Status :: 1 - Planning
Classifier: Intended Audience :: Developers
Classifier: Programming Language :: Python :: 3
Classifier: Operating System :: Unix
Classifier: Operating System :: MacOS :: MacOS X
Classifier: Operating System :: Microsoft :: Windows
Requires-Dist: dash
Requires-Dist: pandas
Requires-Dist: plotly
